casashell/LICENSE.txt
casashell/__init__.py
casashell/__main__.py
casashell/private/accor.py
casashell/private/apparentsens.py
casashell/private/appendantab.py
casashell/private/applycal.py
casashell/private/asdmsummary.py
casashell/private/bandpass.py
casashell/private/blcal.py
casashell/private/builtin_mgr.py
casashell/private/calstat.py
casashell/private/clearcal.py
casashell/private/clearstat.py
casashell/private/concat.py
casashell/private/conjugatevis.py
casashell/private/cvel.py
casashell/private/cvel2.py
casashell/private/deconvolve.py
casashell/private/defintent.py
casashell/private/delmod.py
casashell/private/exportasdm.py
casashell/private/exportfits.py
casashell/private/exportuvfits.py
casashell/private/feather.py
casashell/private/fixplanets.py
casashell/private/fixvis.py
casashell/private/flagcmd.py
casashell/private/flagdata.py
casashell/private/flagmanager.py
casashell/private/fluxscale.py
casashell/private/fringefit.py
casashell/private/ft.py
casashell/private/gaincal.py
casashell/private/gencal.py
casashell/private/getantposalma.py
casashell/private/getcalmodvla.py
casashell/private/getephemtable.py
casashell/private/hanningsmooth.py
casashell/private/imbaseline.py
casashell/private/imcollapse.py
casashell/private/imcontsub.py
casashell/private/imdev.py
casashell/private/imfit.py
casashell/private/imhead.py
casashell/private/imhistory.py
casashell/private/immath.py
casashell/private/immoments.py
casashell/private/impbcor.py
casashell/private/importasap.py
casashell/private/importasdm.py
casashell/private/importatca.py
casashell/private/importfits.py
casashell/private/importfitsidi.py
casashell/private/importgmrt.py
casashell/private/importmiriad.py
casashell/private/importnro.py
casashell/private/importuvfits.py
casashell/private/importvla.py
casashell/private/impv.py
casashell/private/imrebin.py
casashell/private/imreframe.py
casashell/private/imregrid.py
casashell/private/imsmooth.py
casashell/private/imstat.py
casashell/private/imsubimage.py
casashell-6.7.2.42.dist-info/METADATA
casashell-6.7.2.42.dist-info/WHEEL
casashell-6.7.2.42.dist-info/top_level.txt
casashell-6.7.2.42.dist-info/RECORD
