Metadata-Version: 2.4
Name: casashell
Version: 6.7.2.42
Summary: The CASA CLI
Home-page: https://open-bitbucket.nrao.edu/projects/CASA/repos/casatools/browse
Download-URL: https://casa.nrao.edu/download/
Author: CASA development team
Author-email: casa-feedback@nrao.edu
Maintainer: Darrell Schiebel
Maintainer-email: drs@nrao.edu
License: GNU Library or Lesser General Public License (LGPL)
Classifier: Programming Language :: Python :: 3.12
Requires-Dist: casatasks==6.7.2.42
Requires-Dist: casatools
Requires-Dist: matplotlib
Requires-Dist: scipy
Requires-Dist: ipython
Requires-Dist: traitlets
Requires-Dist: pyerfa
Dynamic: author
Dynamic: author-email
Dynamic: classifier
Dynamic: description
Dynamic: download-url
Dynamic: home-page
Dynamic: license
Dynamic: maintainer
Dynamic: maintainer-email
Dynamic: requires-dist
Dynamic: summary
